edna2/__init__.py
edna2/config/__init__.py
edna2/config/default.yaml
edna2/config/esrf.yaml
edna2/config/esrf_bm07.yaml
edna2/config/esrf_icat_prod.yaml
edna2/config/esrf_icat_valid.yaml
edna2/config/esrf_id23eh1.yaml
edna2/config/esrf_id23eh2.yaml
edna2/config/esrf_id23eh2_sim1.yaml
edna2/config/esrf_id29.yaml
edna2/config/esrf_id30a1.yaml
edna2/config/esrf_id30a1_sim1.yaml
edna2/config/esrf_id30a1_sim2.yaml
edna2/config/esrf_id30a1_sim3.yaml
edna2/config/esrf_id30a2.yaml
edna2/config/esrf_id30a3.yaml
edna2/config/esrf_id30b.yaml
edna2/config/esrf_ispyb_prod.yaml
edna2/config/esrf_ispyb_valid.yaml
edna2/lib/markupv1_10/__init__.py
edna2/lib/markupv1_10/markupv1_10.py
edna2/lib/markupv1_10/doc/__init__.py
edna2/lib/markupv1_10/doc/examples.py
edna2/schema/experimentalCondition.json
edna2/schema/imageDozor.json
edna2/schema/imageQualityIndicators.json
edna2/schema/ispybAutoprocIntegration.json
edna2/schema/ispybDataCollection.json
edna2/schema/ispybDiffractionPlan.json
edna2/schema/sample.json
edna2/schema/subWedge.json
edna2/tasks/AbstractTask.py
edna2/tasks/AutoProcessingWrappers.py
edna2/tasks/Best.py
edna2/tasks/CCP4Tasks.py
edna2/tasks/Characterisation.py
edna2/tasks/ControlDozor.py
edna2/tasks/ControlIndexing.py
edna2/tasks/CrystfelTasks.py
edna2/tasks/DIALSFindSpots.py
edna2/tasks/DiffractionThumbnail.py
edna2/tasks/DozorM.py
edna2/tasks/DozorM2.py
edna2/tasks/DozorRD.py
edna2/tasks/H5ToBinnedCBFTask.py
edna2/tasks/H5ToCBFTask.py
edna2/tasks/HelloWorldTask.py
edna2/tasks/ISPyBTasks.py
edna2/tasks/ImageQualityIndicators.py
edna2/tasks/Is4aTasks.py
edna2/tasks/MosflmTasks.py
edna2/tasks/PhenixTasks.py
edna2/tasks/PredictionTasks.py
edna2/tasks/Raddose.py
edna2/tasks/RadiationDamageProcessing.py
edna2/tasks/ReadImageHeader.py
edna2/tasks/SpotPredictionTasks.py
edna2/tasks/SubWedgeAssembly.py
edna2/tasks/WaitFileTask.py
edna2/tasks/XDSTasks.py
edna2/tasks/__init__.py
edna2/tests/__init__.py
edna2/tests/test_tasks/__init__.py
edna2-2.1.0.dist-info/licenses/LICENSE.md
edna2-2.1.0.dist-info/METADATA
edna2-2.1.0.dist-info/WHEEL
edna2-2.1.0.dist-info/top_level.txt
edna2-2.1.0.dist-info/RECORD
